LICENSE
MANIFEST.in
README.md
setup.py
pubdns/__init__.py
pubdns/__version__.py
pubdns/dns.py
pubdns/exceptions.py
pubdns/pubdns.py
pubdns.egg-info/PKG-INFO
pubdns.egg-info/SOURCES.txt
pubdns.egg-info/dependency_links.txt
pubdns.egg-info/requires.txt
pubdns.egg-info/top_level.txt